quat3d/__init__.py
quat3d/jet.stl
quat3d/quat3d.png
quat3d/quat3d.py
quat3d/quat3d_xnode_code.png
quat3d/quaternion3d.py
quat3d-1.0.0.dist-info/LICENSE
quat3d-1.0.0.dist-info/METADATA
quat3d-1.0.0.dist-info/WHEEL
quat3d-1.0.0.dist-info/entry_points.txt
quat3d-1.0.0.dist-info/top_level.txt
quat3d-1.0.0.dist-info/RECORD
