Metadata-Version: 2.1
Name: quat3d
Version: 1.0.0
Summary: This is an IMU quaternion data visualization tool for xkit.
Home-page: https://github.com/planxstudio/xkit
Author: chanmin.park
Author-email: devcamp@gmail.com
Keywords: xkit,genlib
Classifier: Programming Language :: Python :: 3
Classifier: License :: OSI Approved :: MIT License
Classifier: Operating System :: OS Independent
Requires-Python: >=3.11
License-File: LICENSE
Requires-Dist: click
Requires-Dist: python-dotenv
Requires-Dist: pyqt6
Requires-Dist: pyqtgraph
Requires-Dist: pyopengl
Requires-Dist: pyopengl-accelerate
Requires-Dist: numpy-stl
Requires-Dist: genlib
